MANIFEST.in
README.md
setup.cfg
setup.py
core/__init__.py
core/cli_methods.py
core/demo_constants.py
core/main.py
core/tools.py
core/res/__init__.py
core/res/project.tar.gz
core/res/SDK/__init__.py
core/res/SDK/base.py
core/res/SDK/cli.py
core/res/SDK/http_run.py
core/res/SDK/models.py
core/res/SDK/plugin.py
core/res/SDK/run_define.py
core/res/SDK/service_stop.py
core/res/SDK/web.py
mvtech_plugin.egg-info/PKG-INFO
mvtech_plugin.egg-info/SOURCES.txt
mvtech_plugin.egg-info/dependency_links.txt
mvtech_plugin.egg-info/entry_points.txt
mvtech_plugin.egg-info/requires.txt
mvtech_plugin.egg-info/top_level.txt