Metadata-Version: 2.1
Name: mvtech-plugin
Version: 1.10.4
Summary: 插件生成等功能...
Home-page: https://www.mvtech.cn/market/introduction
Author: sandy
Author-email: tong@mvtech.com.cn
License: MIT
Requires-Python: >=3
